mercuryo.py
mercuryo_oor_mcp-0.1.3.dist-info/METADATA
mercuryo_oor_mcp-0.1.3.dist-info/WHEEL
mercuryo_oor_mcp-0.1.3.dist-info/entry_points.txt
mercuryo_oor_mcp-0.1.3.dist-info/top_level.txt
mercuryo_oor_mcp-0.1.3.dist-info/RECORD
