Metadata-Version: 2.4
Name: mercuryo-oor-mcp
Version: 0.1.3
Summary: Simplest way to buy and sell crypto with Mercuryo
Requires-Python: >=3.12
Requires-Dist: mcp[cli]>=1.8.1
